{
  "IconType": "",
  "LightSettings": {
    "HoursPassedStatus": "Keep",
    "SyncLights": true,
    "WorkingDays": "Monday|Tuesday|Wednesday|Thursday|Friday",
    "WorkingHoursStartTime": "",
    "WorkingHoursEndTime": "",
    "UseAmPm": true,
    "UseWorkingHours": false,
    "PollingInterval": 5.0,
    "UseDefaultBrightness": true,
    "DefaultBrightness": 100,
    "LIFX": {
      "LIFXClientId": "",
      "LIFXClientSecret": "",
      "LIFXApiKey": "",
      "IsEnabled": false,
      "SelectedItemId": "",
      "Brightness": 100,
      "UseActivityStatus": false,
      "Statuses": {
        "AvailabilityAvailableStatus": {
          "Disabled": false,
          "Color": "#00ff55"
        },
        "AvailabilityAvailableIdleStatus": {
          "Disabled": false,
          "Color": "#FFFF00"
        },
        "AvailabilityAwayStatus": {
          "Disabled": false,
          "Color": "#FFFF00"
        },
        "AvailabilityBeRightBackStatus": {
          "Disabled": false,
          "Color": "#FFFF00"
        },
        "AvailabilityBusyStatus": {
          "Disabled": false,
          "Color": "#FF3300"
        },
        "AvailabilityBusyIdleStatus": {
          "Disabled": false,
          "Color": "#FFFF00"
        },
        "AvailabilityDoNotDisturbStatus": {
          "Disabled": false,
          "Color": "#B03CDE"
        },
        "AvailabilityOfflineStatus": {
          "Disabled": false,
          "Color": "#FFFFFF"
        },
        "AvailabilityPresenceUnknownStatus": {
          "Disabled": false,
          "Color": "#FFFFFF"
        },
        "AvailabilityOffStatus": {
          "Disabled": false,
          "Color": "#FFFFFF"
        },
        "ActivityAvailableStatus": {
          "Disabled": false,
          "Color": "#4f824f"
        },
        "ActivityAwayStatus": {
          "Disabled": false,
          "Color": "#ffff00"
        },
        "ActivityBeRightBackStatus": {
          "Disabled": false,
          "Color": "#ffff00"
        },
        "ActivityBusyStatus": {
          "Disabled": false,
          "Color": "#ff0000"
        },
        "ActivityDoNotDisturbStatus": {
          "Disabled": false,
          "Color": "#960000"
        },
        "ActivityInACallStatus": {
          "Disabled": false,
          "Color": "#ff0000"
        },
        "ActivityInAConferenceCallStatus": {
          "Disabled": false,
          "Color": "#ff00d4"
        },
        "ActivityInactiveStatus": {
          "Disabled": false,
          "Color": "#ffff00"
        },
        "ActivityInAMeetingStatus": {
          "Disabled": false,
          "Color": "#ff0000"
        },
        "ActivityOfflineStatus": {
          "Disabled": false,
          "Color": "#FFFFFF"
        },
        "ActivityOffWorkStatus": {
          "Disabled": false,
          "Color": "#FFFFFF"
        },
        "ActivityOutOfOfficeStatus": {
          "Disabled": false,
          "Color": "#ae00ff"
        },
        "ActivityPresenceUnknownStatus": {
          "Disabled": false,
          "Color": "#FFFFFF"
        },
        "ActivityPresentingStatus": {
          "Disabled": false,
          "Color": "#960000"
        },
        "ActivityUrgentInterruptionsOnlyStatus": {
          "Disabled": false,
          "Color": "#560061"
        },
        "ActivityOffStatus": {
          "Disabled": false,
          "Color": "#FFFFFF"
        }
      }
    },
    "Hue": {
      "HueApiKey": "",
      "SelectedItemId": "",
      "HueIpAddress": "",
      "RemoteHueClientId": "",
      "RemoteHueClientSecret": "",
      "RemoteHueClientAppName": "",
      "IsEnabled": false,
      "RemoteBridgeId": "",
      "UseRemoteApi": false,
      "Brightness": 100,
      "UseActivityStatus": false,
      "Statuses": {
        "AvailabilityAvailableStatus": {
          "Disabled": false,
          "Color": "#00ff55"
        },
        "AvailabilityAvailableIdleStatus": {
          "Disabled": false,
          "Color": "#FFFF00"
        },
        "AvailabilityAwayStatus": {
          "Disabled": false,
          "Color": "#FFFF00"
        },
        "AvailabilityBeRightBackStatus": {
          "Disabled": false,
          "Color": "#FFFF00"
        },
        "AvailabilityBusyStatus": {
          "Disabled": false,
          "Color": "#FF3300"
        },
        "AvailabilityBusyIdleStatus": {
          "Disabled": false,
          "Color": "#FFFF00"
        },
        "AvailabilityDoNotDisturbStatus": {
          "Disabled": false,
          "Color": "#B03CDE"
        },
        "AvailabilityOfflineStatus": {
          "Disabled": false,
          "Color": "#FFFFFF"
        },
        "AvailabilityPresenceUnknownStatus": {
          "Disabled": false,
          "Color": "#FFFFFF"
        },
        "AvailabilityOffStatus": {
          "Disabled": false,
          "Color": "#FFFFFF"
        },
        "ActivityAvailableStatus": {
          "Disabled": false,
          "Color": "#4f824f"
        },
        "ActivityAwayStatus": {
          "Disabled": false,
          "Color": "#ffff00"
        },
        "ActivityBeRightBackStatus": {
          "Disabled": false,
          "Color": "#ffff00"
        },
        "ActivityBusyStatus": {
          "Disabled": false,
          "Color": "#ff0000"
        },
        "ActivityDoNotDisturbStatus": {
          "Disabled": false,
          "Color": "#960000"
        },
        "ActivityInACallStatus": {
          "Disabled": false,
          "Color": "#ff0000"
        },
        "ActivityInAConferenceCallStatus": {
          "Disabled": false,
          "Color": "#ff00d4"
        },
        "ActivityInactiveStatus": {
          "Disabled": false,
          "Color": "#ffff00"
        },
        "ActivityInAMeetingStatus": {
          "Disabled": false,
          "Color": "#ff0000"
        },
        "ActivityOfflineStatus": {
          "Disabled": false,
          "Color": "#FFFFFF"
        },
        "ActivityOffWorkStatus": {
          "Disabled": false,
          "Color": "#FFFFFF"
        },
        "ActivityOutOfOfficeStatus": {
          "Disabled": false,
          "Color": "#ae00ff"
        },
        "ActivityPresenceUnknownStatus": {
          "Disabled": false,
          "Color": "#FFFFFF"
        },
        "ActivityPresentingStatus": {
          "Disabled": false,
          "Color": "#960000"
        },
        "ActivityUrgentInterruptionsOnlyStatus": {
          "Disabled": false,
          "Color": "#560061"
        },
        "ActivityOffStatus": {
          "Disabled": false,
          "Color": "#FFFFFF"
        }
      }
    },
    "Yeelight": {
      "SelectedItemId": "",
      "IsEnabled": false,
      "Brightness": 100,
      "UseActivityStatus": false,
      "Statuses": {
        "AvailabilityAvailableStatus": {
          "Disabled": false,
          "Color": "#00ff55"
        },
        "AvailabilityAvailableIdleStatus": {
          "Disabled": false,
          "Color": "#FFFF00"
        },
        "AvailabilityAwayStatus": {
          "Disabled": false,
          "Color": "#FFFF00"
        },
        "AvailabilityBeRightBackStatus": {
          "Disabled": false,
          "Color": "#FFFF00"
        },
        "AvailabilityBusyStatus": {
          "Disabled": false,
          "Color": "#FF3300"
        },
        "AvailabilityBusyIdleStatus": {
          "Disabled": false,
          "Color": "#FFFF00"
        },
        "AvailabilityDoNotDisturbStatus": {
          "Disabled": false,
          "Color": "#B03CDE"
        },
        "AvailabilityOfflineStatus": {
          "Disabled": false,
          "Color": "#FFFFFF"
        },
        "AvailabilityPresenceUnknownStatus": {
          "Disabled": false,
          "Color": "#FFFFFF"
        },
        "AvailabilityOffStatus": {
          "Disabled": false,
          "Color": "#FFFFFF"
        },
        "ActivityAvailableStatus": {
          "Disabled": false,
          "Color": "#4f824f"
        },
        "ActivityAwayStatus": {
          "Disabled": false,
          "Color": "#ffff00"
        },
        "ActivityBeRightBackStatus": {
          "Disabled": false,
          "Color": "#ffff00"
        },
        "ActivityBusyStatus": {
          "Disabled": false,
          "Color": "#ff0000"
        },
        "ActivityDoNotDisturbStatus": {
          "Disabled": false,
          "Color": "#960000"
        },
        "ActivityInACallStatus": {
          "Disabled": false,
          "Color": "#ff0000"
        },
        "ActivityInAConferenceCallStatus": {
          "Disabled": false,
          "Color": "#ff00d4"
        },
        "ActivityInactiveStatus": {
          "Disabled": false,
          "Color": "#ffff00"
        },
        "ActivityInAMeetingStatus": {
          "Disabled": false,
          "Color": "#ff0000"
        },
        "ActivityOfflineStatus": {
          "Disabled": false,
          "Color": "#FFFFFF"
        },
        "ActivityOffWorkStatus": {
          "Disabled": false,
          "Color": "#FFFFFF"
        },
        "ActivityOutOfOfficeStatus": {
          "Disabled": false,
          "Color": "#ae00ff"
        },
        "ActivityPresenceUnknownStatus": {
          "Disabled": false,
          "Color": "#FFFFFF"
        },
        "ActivityPresentingStatus": {
          "Disabled": false,
          "Color": "#960000"
        },
        "ActivityUrgentInterruptionsOnlyStatus": {
          "Disabled": false,
          "Color": "#560061"
        },
        "ActivityOffStatus": {
          "Disabled": false,
          "Color": "#FFFFFF"
        }
      }
    },
    "CustomApi": {
      "IsEnabled": false,
      "SelectedItemId": "",
      "Brightness": 100,
      "UseActivityStatus": false,
      "CustomApiAvailable": {
        "Method": "",
        "Uri": ""
      },
      "CustomApiBusy": {
        "Method": "",
        "Uri": ""
      },
      "CustomApiBeRightBack": {
        "Method": "",
        "Uri": ""
      },
      "CustomApiAway": {
        "Method": "",
        "Uri": ""
      },
      "CustomApiDoNotDisturb": {
        "Method": "",
        "Uri": ""
      },
      "CustomApiOffline": {
        "Method": "",
        "Uri": ""
      },
      "CustomApiOff": {
        "Method": "",
        "Uri": ""
      },
      "CustomApiActivityAvailable": {
        "Method": "",
        "Uri": ""
      },
      "CustomApiActivityInACall": {
        "Method": "",
        "Uri": ""
      },
      "CustomApiActivityInAConferenceCall": {
        "Method": "",
        "Uri": ""
      },
      "CustomApiActivityInAMeeting": {
        "Method": "",
        "Uri": ""
      },
      "CustomApiActivityPresenting": {
        "Method": "",
        "Uri": ""
      },
      "CustomApiActivityBusy": {
        "Method": "",
        "Uri": ""
      },
      "CustomApiActivityAway": {
        "Method": "",
        "Uri": ""
      },
      "CustomApiAvailableIdle": {
        "Method": "",
        "Uri": ""
      },
      "CustomApiActivityBeRightBack": {
        "Method": "",
        "Uri": ""
      },
      "CustomApiActivityDoNotDisturb": {
        "Method": "",
        "Uri": ""
      },
      "CustomApiActivityIdle": {
        "Method": "",
        "Uri": ""
      },
      "CustomApiActivityOffline": {
        "Method": "",
        "Uri": ""
      },
      "CustomApiActivityOff": {
        "Method": "",
        "Uri": ""
      },
      "CustomApiActivityOffWork": {
        "Method": "",
        "Uri": ""
      },
      "CustomApiTimeout": 100,
      "IgnoreCertificateErrors": false,
      "UseBasicAuth": false,
      "BasicAuthUserName": "",
      "BasicAuthUserPassword": ""
    },
    "LocalSerialHost": {
      "IsEnabled": false,
      "SelectedItemId": "",
      "Brightness": 100,
      "UseActivityStatus": false,
      "BaudRate": "",
      "PortNumber": "",
      "LocalSerialHostMainSetup": {
        "BaudRate": "",
        "LineEnding": "",
        "Port": ""
      },
      "LocalSerialHostAvailable": "",
      "LocalSerialHostBusy": "",
      "LocalSerialHostBeRightBack": "",
      "LocalSerialHostAway": "",
      "LocalSerialHostDoNotDisturb": "",
      "LocalSerialHostOffline": "",
      "LocalSerialHostOff": "",
      "LocalSerialHostActivityAvailable": "",
      "LocalSerialHostActivityInACall": "",
      "LocalSerialHostActivityInAConferenceCall": "",
      "LocalSerialHostActivityInAMeeting": "",
      "LocalSerialHostActivityPresenting": "",
      "LocalSerialHostActivityBusy": "",
      "LocalSerialHostActivityAway": "",
      "LocalSerialHostAvailableIdle": "",
      "LocalSerialHostActivityBeRightBack": "",
      "LocalSerialHostActivityDoNotDisturb": "",
      "LocalSerialHostActivityIdle": "",
      "LocalSerialHostActivityOffline": "",
      "LocalSerialHostActivityOff": ""
    },
    "Wiz": {
      "SelectedItemId": "",
      "Brightness": 100,
      "IsEnabled": false,
      "UseActivityStatus": false,
      "Statuses": {
        "AvailabilityAvailableStatus": {
          "Disabled": false,
          "Color": "#00ff55"
        },
        "AvailabilityAvailableIdleStatus": {
          "Disabled": false,
          "Color": "#FFFF00"
        },
        "AvailabilityAwayStatus": {
          "Disabled": false,
          "Color": "#FFFF00"
        },
        "AvailabilityBeRightBackStatus": {
          "Disabled": false,
          "Color": "#FFFF00"
        },
        "AvailabilityBusyStatus": {
          "Disabled": false,
          "Color": "#FF3300"
        },
        "AvailabilityBusyIdleStatus": {
          "Disabled": false,
          "Color": "#FFFF00"
        },
        "AvailabilityDoNotDisturbStatus": {
          "Disabled": false,
          "Color": "#B03CDE"
        },
        "AvailabilityOfflineStatus": {
          "Disabled": false,
          "Color": "#FFFFFF"
        },
        "AvailabilityPresenceUnknownStatus": {
          "Disabled": false,
          "Color": "#FFFFFF"
        },
        "AvailabilityOffStatus": {
          "Disabled": false,
          "Color": "#FFFFFF"
        },
        "ActivityAvailableStatus": {
          "Disabled": false,
          "Color": "#4f824f"
        },
        "ActivityAwayStatus": {
          "Disabled": false,
          "Color": "#ffff00"
        },
        "ActivityBeRightBackStatus": {
          "Disabled": false,
          "Color": "#ffff00"
        },
        "ActivityBusyStatus": {
          "Disabled": false,
          "Color": "#ff0000"
        },
        "ActivityDoNotDisturbStatus": {
          "Disabled": false,
          "Color": "#960000"
        },
        "ActivityInACallStatus": {
          "Disabled": false,
          "Color": "#ff0000"
        },
        "ActivityInAConferenceCallStatus": {
          "Disabled": false,
          "Color": "#ff00d4"
        },
        "ActivityInactiveStatus": {
          "Disabled": false,
          "Color": "#ffff00"
        },
        "ActivityInAMeetingStatus": {
          "Disabled": false,
          "Color": "#ff0000"
        },
        "ActivityOfflineStatus": {
          "Disabled": false,
          "Color": "#FFFFFF"
        },
        "ActivityOffWorkStatus": {
          "Disabled": false,
          "Color": "#FFFFFF"
        },
        "ActivityOutOfOfficeStatus": {
          "Disabled": false,
          "Color": "#ae00ff"
        },
        "ActivityPresenceUnknownStatus": {
          "Disabled": false,
          "Color": "#FFFFFF"
        },
        "ActivityPresentingStatus": {
          "Disabled": false,
          "Color": "#960000"
        },
        "ActivityUrgentInterruptionsOnlyStatus": {
          "Disabled": false,
          "Color": "#560061"
        },
        "ActivityOffStatus": {
          "Disabled": false,
          "Color": "#FFFFFF"
        }
      }
    }
  }
}